cfgr/__init__.py
cfgr/manager.py
cfgr/reader.py
cfgr/utils/__init__.py
ucfgr-0.0.3.dist-info/METADATA
ucfgr-0.0.3.dist-info/WHEEL
ucfgr-0.0.3.dist-info/top_level.txt
ucfgr-0.0.3.dist-info/RECORD
